wwb_scanner/__init__.py
wwb_scanner/core.py
wwb_scanner/file_handlers/__init__.py
wwb_scanner/file_handlers/exporters.py
wwb_scanner/file_handlers/importers.py
wwb_scanner/scan_objects/__init__.py
wwb_scanner/scan_objects/sample.py
wwb_scanner/scan_objects/samplearray.py
wwb_scanner/scan_objects/spectrum.py
wwb_scanner/scanner/__init__.py
wwb_scanner/scanner/config.py
wwb_scanner/scanner/main.py
wwb_scanner/scanner/rtlpower_scan.py
wwb_scanner/scanner/sample_processing.py
wwb_scanner/scanner/sdrwrapper.py
wwb_scanner/ui/__init__.py
wwb_scanner/ui/plots.py
wwb_scanner/ui/pyside/__init__.py
wwb_scanner/ui/pyside/device_config.py
wwb_scanner/ui/pyside/graph.py
wwb_scanner/ui/pyside/main.py
wwb_scanner/ui/pyside/scanner.py
wwb_scanner/ui/pyside/utils.py
wwb_scanner/ui/pyside/qml/ChartSelect.qml
wwb_scanner/ui/pyside/qml/ChartSelectDelegate.qml
wwb_scanner/ui/pyside/qml/Crosshair.qml
wwb_scanner/ui/pyside/qml/DeviceConfigPopup.qml
wwb_scanner/ui/pyside/qml/ExportDialog.qml
wwb_scanner/ui/pyside/qml/Graph.qml
wwb_scanner/ui/pyside/qml/GraphHViewControls.qml
wwb_scanner/ui/pyside/qml/GraphViewController.qml
wwb_scanner/ui/pyside/qml/ImportDialog.qml
wwb_scanner/ui/pyside/qml/LiveSpectrumGraph.qml
wwb_scanner/ui/pyside/qml/NumberInput.qml
wwb_scanner/ui/pyside/qml/ScanConfig.qml
wwb_scanner/ui/pyside/qml/ScanControls.qml
wwb_scanner/ui/pyside/qml/ScanControlsDialog.qml
wwb_scanner/ui/pyside/qml/SpectrumGraph.qml
wwb_scanner/ui/pyside/qml/ThemeSelectPopup.qml
wwb_scanner/ui/pyside/qml/UHFChannel.qml
wwb_scanner/ui/pyside/qml/UHFChannels.qml
wwb_scanner/ui/pyside/qml/ViewScale.qml
wwb_scanner/ui/pyside/qml/ViewXYScale.qml
wwb_scanner/ui/pyside/qml/XScrollBar.qml
wwb_scanner/ui/pyside/qml/main.qml
wwb_scanner/utils/__init__.py
wwb_scanner/utils/color.py
wwb_scanner/utils/config.py
wwb_scanner/utils/dbmath.py
wwb_scanner/utils/dbstore.py
wwb_scanner/utils/numpyjson.py
rtlsdr_wwb_scanner-0.0.1.dist-info/LICENSE
rtlsdr_wwb_scanner-0.0.1.dist-info/METADATA
rtlsdr_wwb_scanner-0.0.1.dist-info/WHEEL
rtlsdr_wwb_scanner-0.0.1.dist-info/entry_points.txt
rtlsdr_wwb_scanner-0.0.1.dist-info/top_level.txt
rtlsdr_wwb_scanner-0.0.1.dist-info/RECORD
