Metadata-Version: 2.1
Name: rtlsdr-wwb-scanner
Version: 0.0.1
Summary: RF Scanner and Exporter for use with Shure Wireless Workbench
Home-page: https://github.com/nocarryr/rtlsdr-wwb-scanner
Author: Matthew Reid
Author-email: matt@nomadic-recording.com
License: GNU General Public License v2 (GPLv2)
Platform: any
Classifier: Development Status :: 3 - Alpha
Classifier: License :: OSI Approved :: GNU General Public License v2 (GPLv2)
Classifier: Topic :: Multimedia :: Sound/Audio
Classifier: Programming Language :: Python :: 3
Classifier: Programming Language :: Python :: 3.5
Classifier: Programming Language :: Python :: 3.6
Classifier: Programming Language :: Python :: 3.7
Requires-Dist: numpy (>=1.13)
Requires-Dist: scipy
Requires-Dist: pyrtlsdr (>=0.2.6)
Requires-Dist: tinydb
Requires-Dist: json-object-factory
Requires-Dist: PySide2 (>=5.13.1)
